ChangeLog
LICENSE
MANIFEST.in
README.md
README.rst
dmesg_format_dates
dmesg_get_drifts
printk_mark_drift
printk_time_convert
setup.py
doc/index.html
doc/printk_timestamp_converter.html
printk_timestamp_converter/__init__.py
printk_timestamp_converter.egg-info/PKG-INFO
printk_timestamp_converter.egg-info/SOURCES.txt
printk_timestamp_converter.egg-info/dependency_links.txt
printk_timestamp_converter.egg-info/top_level.txt