Metadata-Version: 1.1
Name: printk-timestamp-converter
Version: 3.0.0
Summary: Utility for printing dmesg/kmsg/printk timestamps, taking into account drift.
Home-page: https://github.com/kata198/printk-timestamp-converter
Author: Tim Savannah
Author-email: kata198@gmail.com
License: LGPLv2
Keywords: printk,timestamp,date,convert,drift,converter,dmesg,kmsg
Platform: UNKNOWN
Classifier: Development Status :: 5 - Production/Stable
Classifier: Operating System :: POSIX :: Linux
Classifier: Topic :: System :: Operating System Kernels :: Linux
